mrmr/__init__.py
mrmr/bigquery.py
mrmr/main.py
mrmr/pandas.py
mrmr/polars.py
mrmr/spark.py
mrmr_selection-0.2.8.dist-info/LICENSE
mrmr_selection-0.2.8.dist-info/METADATA
mrmr_selection-0.2.8.dist-info/WHEEL
mrmr_selection-0.2.8.dist-info/top_level.txt
mrmr_selection-0.2.8.dist-info/RECORD
