Metadata-Version: 2.1
Name: mrmr-selection
Version: 0.2.8
Summary: minimum-Redundancy-Maximum-Relevance algorithm for feature selection
Home-page: https://github.com/smazzanti/mrmr
Author: Samuele Mazzanti
Author-email: mazzanti.sam@gmail.com
License: GNU General Public License v3.0
Platform: UNKNOWN
License-File: LICENSE
Requires-Dist: category-encoders
Requires-Dist: jinja2
Requires-Dist: tqdm
Requires-Dist: joblib
Requires-Dist: pandas (>=1.0.3)
Requires-Dist: numpy (>=1.18.1)
Requires-Dist: scikit-learn
Requires-Dist: scipy
Requires-Dist: polars (>=0.12.5)
